testpypackage_ces/__init__.py
testpypackage_ces/example.py
testpypackage_ces-0.0.9.dist-info/LICENSE.txt
testpypackage_ces-0.0.9.dist-info/METADATA
testpypackage_ces-0.0.9.dist-info/WHEEL
testpypackage_ces-0.0.9.dist-info/top_level.txt
testpypackage_ces-0.0.9.dist-info/RECORD
